llmcompiler/__init__.py
llmcompiler/chat/__init__.py
llmcompiler/chat/launch.py
llmcompiler/chat/run.py
llmcompiler/custom_llms/__init__.py
llmcompiler/custom_llms/claude.py
llmcompiler/custom_llms/openai.py
llmcompiler/few_shot/__init__.py
llmcompiler/few_shot/example.py
llmcompiler/few_shot/few_shot.py
llmcompiler/few_shot/generate.py
llmcompiler/graph/__init__.py
llmcompiler/graph/joiner.py
llmcompiler/graph/output_parser.py
llmcompiler/graph/plan_and_schedule.py
llmcompiler/graph/planner.py
llmcompiler/graph/prompt.py
llmcompiler/graph/rewrite.py
llmcompiler/graph/token_calculate.py
llmcompiler/graph/tool_message.py
llmcompiler/result/__init__.py
llmcompiler/result/chat.py
llmcompiler/service/__init__.py
llmcompiler/service/status.py
llmcompiler/tools/__init__.py
llmcompiler/tools/basic.py
llmcompiler/tools/prompt.py
llmcompiler/tools/tools.py
llmcompiler/tools/basetool/__init__.py
llmcompiler/tools/basetool/fund_basic_v1.py
llmcompiler/tools/basetool/fund_basic_v2.py
llmcompiler/tools/basetool/multi_param_dep_v1.py
llmcompiler/tools/basetool/multi_param_dep_v2.py
llmcompiler/tools/basetool/multi_param_dep_v3.py
llmcompiler/tools/basetool/stock_info_fake.py
llmcompiler/tools/basetool/tool_decorator.py
llmcompiler/tools/configure/__init__.py
llmcompiler/tools/configure/kwargs_clear.py
llmcompiler/tools/configure/pydantic_oper.py
llmcompiler/tools/configure/tool_decorator.py
llmcompiler/tools/dag/__init__.py
llmcompiler/tools/dag/dag_flow_params.py
llmcompiler/tools/eval/__init__.py
llmcompiler/tools/generic/__init__.py
llmcompiler/tools/generic/action_input.py
llmcompiler/tools/generic/action_output.py
llmcompiler/tools/generic/render_description.py
llmcompiler/tools/math/__init__.py
llmcompiler/tools/math/math_tools.py
llmcompiler/utils/__init__.py
llmcompiler/utils/const/__init__.py
llmcompiler/utils/date/__init__.py
llmcompiler/utils/date/date.py
llmcompiler/utils/prompt/__init__.py
llmcompiler/utils/prompt/prompt.py
llmcompiler/utils/string/__init__.py
llmcompiler-2.0.1.dist-info/licenses/LICENSE
llmcompiler-2.0.1.dist-info/METADATA
llmcompiler-2.0.1.dist-info/WHEEL
llmcompiler-2.0.1.dist-info/top_level.txt
llmcompiler-2.0.1.dist-info/RECORD
