Metadata-Version: 2.4
Name: llmcompiler
Version: 2.0.1
Summary: LLMCompiler
Author-email: Yc-Ma <yanchaoma@foxmail.com>
License: Apache-2.0
Project-URL: Homepage, https://github.com/crazyyanchao/llmcompiler
Keywords: LLMCompiler,Agent,Natural Language Processing,LLM,Machine Learning,AI,Compiler
Classifier: Development Status :: 4 - Beta
Classifier: Intended Audience :: Developers
Classifier: Topic :: Software Development :: Libraries :: Python Modules
Classifier: Programming Language :: Python :: 3
Classifier: License :: OSI Approved :: Apache Software License
Classifier: Operating System :: OS Independent
Requires-Python: >=3.11
License-File: LICENSE
Requires-Dist: langgraph>=1.0.1
Requires-Dist: langchain>=1.0.2
Requires-Dist: langchain-openai>=1.0.1
Requires-Dist: pandas>=2.3.3
Requires-Dist: grandalf>=0.8
Dynamic: license-file
